{"time":"2023-03-20 15:09:43 +0900","data":[{"name":"アルペン","id":533,"s_name":"alpen","kana":"あるぺん","group1":"","genre1":"","genre2":"","genre3":"","hp_url":"https://store.alpen-group.jp/","img_url":"https://www.tokuppa.com/app/image/shop/shop.png","app_name":"","app_url":"https://store.alpen-group.jp/","ios_app":"https://apps.apple.com/jp/app/id1455474437","android_app":"https://play.google.com/store/apps/details?id=li.yapp.app7C057045&hl=ja","Twitter":"","Instagram":"","LINE":"","facebook":"","youtube":"","find_store_url":"","chirashi_url":"","campaign_url":"","fair_url":"","menu_url":"","net_url":"","cal":"jvvpt02ms1ft2pkkceh81k3nn0@group.calendar.google.com","note":""},{"P0004":{"way":"extax_mai","w1":200.0,"w2":1.0,"w3":"","rate":0.005}},{"point_h":"","P1321":""},{"CC0001":"","CC0002":"","CC0003":"","CC0004":""},{},{"CQ0001":"","CQ0002":"","CQ0003":"","CQ0004":"","CQ0005":"","CQ0006":""},{},{"P0004":[{"id":968,"s_name":"alpen","c_id":968,"card_id":"P0004","c_name":"対象のアルペングループ +3%楽天ポイント還元","way":"per_back_plus","w1":0.03,"w2":"","w3":"","rate":0.03,"min":200.0,"max_once":500.0,"max_term":"","max_times":"","user":"","no_user":"","detail":"エントリーのうえ、対象店舗で条件を満たしたお買い物で店頭購入金額(税抜)の3％ポイント還元\n1会計あたりの最低お買い物金額200円(税抜)以上\n対象店舗：東京都、神奈川県、埼玉県、千葉県の一部店舗\n※対象購入金額は税抜、送料別、クーポン適用後の金額です。\n※対象期間内であっても、エントリー前のお買い物は当キャンペーンの対象外となります。\n※ご購入1回につき最大500ポイント","img_url":"https://www.tokuppa.com/app/image/campaign/rakutenpoint202212alpen.png","d_URL":"https://event.rakuten.co.jp/sports/alpen/city/","iosURL":"","androidURL":"","start":"2022-12-16 00:00:00 +0900","end":"2023-04-30 23:59:00 +0900","day":"","same_cam":"","give_date":"2000-01-01 00:00:00 +0900","entry":"need","note":"","cal":"N"}]},{},{},{},[],[],[],[]]}