{"time":"2024-02-19 12:09:35 +0900","data":[{"name":"バースディ","id":413,"s_name":"birthday","kana":"ばーすでぃ","group1":"しまむら","genre1":"ファッション","genre2":"子供服","genre3":"","hp_url":"https://www.s-birthday.com/","img_url":"https://www.tokuppa.com/app/image/shop/shop.png","app_name":"","app_url":"https://www.shimamura.gr.jp/sns/index_pc_211207.php","ios_app":"https://apps.apple.com/jp/app/basudei/id759460885","android_app":"https://play.google.com/store/apps/details?id=biz.shopup.birthday","Twitter":"https://twitter.com/birthday_gr","Instagram":"https://instagram.com/grbirthday/","LINE":"https://line.me/R/ti/p/@birthday?from=page","facebook":"https://www.facebook.com/birthday.gr","youtube":"","find_store_url":"https://www.s-birthday.com/category/open/","chirashi_url":"https://www.shimamura.gr.jp/birthday/flier/","campaign_url":"","fair_url":"","menu_url":"","net_url":"","cal":"o05e3a0hq22n6k9nqgpcq4c3f0@group.calendar.google.com","note":""},{},{"point_h":""},{"CC0001":"","CC0002":"","CC0003":"","CC0004":""},{"CE0001":{"way":"T","w1":0.0,"w2":0.0,"w3":"","rate":0.0},"CE0002":{"way":"intax_mai","w1":200.0,"w2":1.0,"w3":"","rate":0.005},"CE0003":{"way":"intax_mai","w1":200.0,"w2":1.0,"w3":"","rate":0.005},"CE0004":{"way":"intax_mai","w1":200.0,"w2":1.0,"w3":"","rate":0.005},"CE0005":{"way":"T","w1":0.0,"w2":0.0,"w3":"","rate":0.0},"CE0006":{"way":"T","w1":0.0,"w2":0.0,"w3":"","rate":0.0}},{"CQ0001":""},{},{},{},{},{},[],[],[],[]]}