{"time":"2024-02-19 12:09:39 +0900","data":{"coupon2":{},"all_campaign2":[{"id":1972,"s_name":"keio-dept","c_id":1972,"card_id":"P0003","c_name":"京王百貨店｜食品フロア限定dポイント2倍","way":"bai_back_plus","w1":2.0,"w2":"","w3":"","rate":2.0,"min":"","max_once":"","max_term":1000.0,"max_times":"","user":"","no_user":"","detail":"期間中キャンペーンサイトからエントリーの上京王百貨店の対象店舗でお会計の際にdポイントカードをご提示いただくと通常の2倍（通常ポイント1倍分＋キャンペーンポイント1倍分）のポイントを進呈します。\nさらに、期間中3日以上ご来店・お会計いただいた方にはもれなくdポイント100ポイント（期間・用途限定）進呈いたします。\n※進呈ポイントの上限は期間中お一人さま1,000ポイントです。","img_url":"https://www.tokuppa.com/app/image/campaign/dpoint202309_240118_659119_659122.jpg","d_URL":"https://dpoint.docomo.ne.jp/cp_2/keio-d_230927_4668/index.html","iosURL":"","androidURL":"","start":"2023-09-27 00:00:00 +0900","end":"2023-10-18 23:59:00 +0900","day":"","same_cam":"","give_date":"2000-01-01 00:00:00 +0900","entry":"need","note":"","cal":"N"},{"id":1267,"s_name":"keio-dept","c_id":1267,"card_id":"P0003","c_name":"京王百貨店 dポイント2倍キャンペーン","way":"bai_back_plus","w1":"","w2":"","w3":"","rate":"","min":"","max_once":"","max_term":1000.0,"max_times":"","user":"","no_user":"","detail":"期間中キャンペーンサイトからエントリーの上京王百貨店の対象店舗でお会計の際にdポイントカードをご提示いただくと通常の2倍（通常ポイント1倍分＋キャンペーンポイント1倍分）のポイントを進呈します。\n※進呈ポイントの上限は期間中お一人さま1,000ポイントです。","img_url":"https://www.tokuppa.com/app/image/campaign/dpoint202303keio_dept.png","d_URL":"https://dpoint.docomo.ne.jp/cp_2/keio-d_230302_3994/index.html","iosURL":"","androidURL":"","start":"2023-03-02 00:00:00 +0900","end":"2023-03-15 23:59:00 +0900","day":"","same_cam":"","give_date":"2000-01-01 00:00:00 +0900","entry":"need","note":"","cal":"N"}]}}