{"time":"2024-02-19 12:09:47 +0900","data":{"coupon2":{},"all_campaign2":[{"id":2005,"s_name":"kaikatsu-club","c_id":2005,"card_id":"CQ0001","c_name":"PayPayクーポン(ソフトバンク限定) 快活CLUB 10%","way":"per_back_plus","w1":"","w2":"","w3":"","rate":0.1,"min":"","max_once":200.0,"max_term":200.0,"max_times":1.0,"user":"softbank","no_user":"","detail":"事前にセットが必要です\nソフトバンク会員限定です","img_url":"https://www.tokuppa.com/app/image/campaign/paypaycoupon_softbank.png","d_URL":"https://paypay.ne.jp/event/super-paypay-coupon/?appwebview","iosURL":"","androidURL":"","start":"2023-10-01 00:00:00 +0900","end":"2023-10-31 23:59:00 +0900","day":"","same_cam":"","give_date":"2000-01-01 00:00:00 +0900","entry":"","note":"","cal":"N"}]}}